{
  "name": "Ei Ei Nyein",
  "position": "Freelance Accountant",
  "email": "eieinyeinacc@gmail.com",
  "mobile_no": "09252442672",
  "image": "images/profile.jpg",
  "address": "Yangon",
  "father_name": "U Win",
  "citizenship": "Myanmar",
  "gender": "Female",
  "about_me": "I am an accountant with 14 years of experience of ledger processes, reconciliations and reports. I am an account handler with strong interpersonal skills, highly creative and motivated to help business acquire and maintain clients long-term.",
}
